keywordsai_sdk/__init__.py
keywordsai_sdk/constants/__init__.py
keywordsai_sdk/constants/_internal_constants.py
keywordsai_sdk/constants/dataset_constants.py
keywordsai_sdk/constants/evaluation_constants.py
keywordsai_sdk/constants/experiment_constants.py
keywordsai_sdk/constants/llm_logging.py
keywordsai_sdk/constants/prompt_constants.py
keywordsai_sdk/keywordsai_types/__init__.py
keywordsai_sdk/keywordsai_types/_internal_types.py
keywordsai_sdk/keywordsai_types/base_types.py
keywordsai_sdk/keywordsai_types/chat_completion_types.py
keywordsai_sdk/keywordsai_types/dataset_types.py
keywordsai_sdk/keywordsai_types/eval_types.py
keywordsai_sdk/keywordsai_types/evaluator_types.py
keywordsai_sdk/keywordsai_types/experiment_types.py
keywordsai_sdk/keywordsai_types/filter_types.py
keywordsai_sdk/keywordsai_types/generic_types.py
keywordsai_sdk/keywordsai_types/log_types.py
keywordsai_sdk/keywordsai_types/mixin_types/__init__.py
keywordsai_sdk/keywordsai_types/mixin_types/filter_mixin.py
keywordsai_sdk/keywordsai_types/monitoring_types.py
keywordsai_sdk/keywordsai_types/param_types.py
keywordsai_sdk/keywordsai_types/prompt_types.py
keywordsai_sdk/keywordsai_types/prompt_types.py.backup
keywordsai_sdk/keywordsai_types/services_types/__init__.py
keywordsai_sdk/keywordsai_types/services_types/assembly_ai_types.py
keywordsai_sdk/keywordsai_types/services_types/linkup_types.py
keywordsai_sdk/keywordsai_types/services_types/mem0_types.py
keywordsai_sdk/keywordsai_types/services_types/moda_types.py
keywordsai_sdk/keywordsai_types/span_types.py
keywordsai_sdk/keywordsai_types/user_types.py
keywordsai_sdk/utils/__init__.py
keywordsai_sdk/utils/bgcolors.py
keywordsai_sdk/utils/crypto.py
keywordsai_sdk/utils/data_processing/__init__.py
keywordsai_sdk/utils/data_processing/id_processing.py
keywordsai_sdk/utils/debug_print.py
keywordsai_sdk/utils/mixins.py
keywordsai_sdk/utils/pre_processing.py
keywordsai_sdk/utils/serialization.py
keywordsai_sdk/utils/time.py
keywordsai_sdk-0.5.2.dist-info/METADATA
keywordsai_sdk-0.5.2.dist-info/WHEEL
keywordsai_sdk-0.5.2.dist-info/RECORD
