Metadata-Version: 2.1
Name: keywordsai-sdk
Version: 0.5.2
Summary: Keywords AI SDK allows you to interact with the Keywords AI API smoothly
License: MIT
Author: Keywords AI
Author-email: team@keywordsai.co
Requires-Python: >3.9,<4.0
Classifier: License :: OSI Approved :: MIT License
Classifier: Programming Language :: Python :: 3
Classifier: Programming Language :: Python :: 3.10
Classifier: Programming Language :: Python :: 3.11
Classifier: Programming Language :: Python :: 3.12
Provides-Extra: dev
Requires-Dist: dateparser (>=1.2.0,<2.0.0)
Requires-Dist: pydantic (>=2.10.3,<3.0.0)
Requires-Dist: requests (>=2.31.0,<3.0.0)
Requires-Dist: typing-extensions (>=4.12.2,<5.0.0)
